plot_diagram_eye/__init__.py
plot_diagram_eye/main.py
plot_diagram_eye-0.1.0.dist-info/METADATA
plot_diagram_eye-0.1.0.dist-info/WHEEL
plot_diagram_eye-0.1.0.dist-info/top_level.txt
plot_diagram_eye-0.1.0.dist-info/RECORD
