Metadata-Version: 2.1
Name: plot_diagram_eye
Version: 0.1.0
Summary: A library designed to generate and visualize eye diagrams for digital communication signals. 
Home-page: https://github.com/yourusername/eye_diagram
Author: K ABHISHEK MENON
Author-email: kabhishekmenon@gmail.com
Classifier: Programming Language :: Python :: 3
Classifier: License :: OSI Approved :: MIT License
Classifier: Operating System :: OS Independent
Classifier: Development Status :: 3 - Alpha
Classifier: Intended Audience :: Science/Research
Classifier: Topic :: Scientific/Engineering :: Information Analysis
Requires-Python: >=3.6
Requires-Dist: numpy >=1.18.0
Requires-Dist: matplotlib >=3.1.0
